pal_api-0.1.1.dist-info/METADATA
pal_api-0.1.1.dist-info/WHEEL
pal_api-0.1.1.dist-info/licenses/LICENSE
pal_api/__init__.py
pal_api/async_client.py
pal_api/client.py
pal_api/errors.py
pal_api/models.py
pal_api-0.1.1.dist-info/RECORD
