Metadata-Version: 2.1
Name: pal_api
Version: 0.1.1
Summary: API Wrapper for Palworld Dedicated Server
Home-page: https://github.com/Charahiro-tan/pal_api
Author-Email: Charahiro-tan <charahiro.tan@gmail.com>
License: MIT
Classifier: License :: OSI Approved :: MIT License
Classifier: Natural Language :: Japanese
Classifier: Programming Language :: Python :: 3
Project-URL: Homepage, https://github.com/Charahiro-tan/pal_api
Requires-Python: >=3.10
Requires-Dist: aiohttp>=3.9.4
